apilinker/__init__.py
apilinker/__main__.py
apilinker/api_linker.py
apilinker/cli.py
apilinker/connectors/__init__.py
apilinker/connectors/general/__init__.py
apilinker/connectors/general/github.py
apilinker/connectors/general/nasa.py
apilinker/connectors/scientific/__init__.py
apilinker/connectors/scientific/arxiv.py
apilinker/connectors/scientific/crossref.py
apilinker/connectors/scientific/ncbi.py
apilinker/connectors/scientific/orcid.py
apilinker/connectors/scientific/pubchem.py
apilinker/connectors/scientific/semantic_scholar.py
apilinker/core/__init__.py
apilinker/core/async_connector.py
apilinker/core/auth.py
apilinker/core/connector.py
apilinker/core/error_handling.py
apilinker/core/idempotency.py
apilinker/core/logger.py
apilinker/core/mapper.py
apilinker/core/message_queue.py
apilinker/core/message_queue_connectors.py
apilinker/core/monitoring.py
apilinker/core/observability.py
apilinker/core/plugins.py
apilinker/core/provenance.py
apilinker/core/rate_limiting.py
apilinker/core/scheduler.py
apilinker/core/schema_probe.py
apilinker/core/secrets.py
apilinker/core/security.py
apilinker/core/security_integration.py
apilinker/core/state_store.py
apilinker/core/validation.py
apilinker/core/webhooks.py
apilinker/plugins/__init__.py
apilinker/plugins/builtin.py
apilinker-0.6.1.dist-info/licenses/LICENSE
apilinker-0.6.1.dist-info/METADATA
apilinker-0.6.1.dist-info/WHEEL
apilinker-0.6.1.dist-info/entry_points.txt
apilinker-0.6.1.dist-info/top_level.txt
apilinker-0.6.1.dist-info/RECORD
