Metadata-Version: 2.4
Name: apilinker
Version: 0.6.1
Summary: A universal bridge to connect, map, and automate data transfer between any two REST APIs
Home-page: https://github.com/kkartas/APILinker
Author: K. Kartas
Author-email: "K. Kartas" <kkartas@users.noreply.github.com>
License: MIT
Project-URL: Homepage, https://github.com/kkartas/APILinker
Project-URL: Bug Tracker, https://github.com/kkartas/APILinker/issues
Project-URL: Documentation, https://apilinker.readthedocs.io/
Keywords: api,integration,connector,data transfer,rest
Classifier: Development Status :: 4 - Beta
Classifier: Intended Audience :: Developers
Classifier: License :: OSI Approved :: MIT License
Classifier: Programming Language :: Python :: 3
Classifier: Programming Language :: Python :: 3.8
Classifier: Programming Language :: Python :: 3.9
Classifier: Programming Language :: Python :: 3.10
Classifier: Programming Language :: Python :: 3.11
Requires-Python: >=3.8
License-File: LICENSE
Requires-Dist: httpx>=0.23.0
Requires-Dist: pyyaml>=6.0
Requires-Dist: typer>=0.7.0
Requires-Dist: pydantic>=2.0.0
Requires-Dist: croniter>=1.3.8
Requires-Dist: rich>=12.6.0
Requires-Dist: cryptography>=41.0.0
Requires-Dist: jsonschema>=4.18.0
Provides-Extra: dev
Requires-Dist: pytest>=7.0.0; extra == "dev"
Requires-Dist: pytest-cov>=4.0.0; extra == "dev"
Requires-Dist: flake8>=6.0.0; extra == "dev"
Requires-Dist: mypy>=1.0.0; extra == "dev"
Requires-Dist: types-croniter; extra == "dev"
Requires-Dist: types-PyYAML; extra == "dev"
Requires-Dist: black>=23.0.0; extra == "dev"
Requires-Dist: bump-my-version>=0.18.0; extra == "dev"
Provides-Extra: mq
Requires-Dist: pika>=1.3.0; extra == "mq"
Requires-Dist: redis>=5.0.0; extra == "mq"
Requires-Dist: boto3>=1.28.0; extra == "mq"
Requires-Dist: kafka-python>=2.0.2; extra == "mq"
Provides-Extra: docs
Requires-Dist: mkdocs>=1.5.0; extra == "docs"
Requires-Dist: mkdocs-material>=9.5.0; extra == "docs"
Requires-Dist: mkdocstrings[python]>=0.24.0; extra == "docs"
Requires-Dist: mkdocs-minify-plugin>=0.7.0; extra == "docs"
Requires-Dist: mkdocs-git-revision-date-localized-plugin>=1.2.0; extra == "docs"
Provides-Extra: webhooks
Requires-Dist: fastapi>=0.100.0; extra == "webhooks"
Requires-Dist: uvicorn>=0.23.0; extra == "webhooks"
Requires-Dist: pyjwt>=2.8.0; extra == "webhooks"
Dynamic: author
Dynamic: home-page
Dynamic: license-file
